LICENSE.txt
po/__init__.py
po/case_conversion/__init__.py
po/case_conversion/case_conversion.py
po/case_conversion/case_parse.py
po.case_conversion-0.2.0.dist-info/LICENSE.txt
po.case_conversion-0.2.0.dist-info/WHEEL
po.case_conversion-0.2.0.dist-info/METADATA
po.case_conversion-0.2.0.dist-info/RECORD
