Metadata-Version: 2.1
Name: po.case-conversion
Version: 0.2.0
Summary: Convert between different types of cases (unicode supported)
Home-page: https://github.com/olsonpm/case-conversion
License: MIT
Author: Alejandro Frias
Author-email: joker454@gmail.com
Requires-Python: >=3.7,<4.0
Classifier: License :: OSI Approved :: MIT License
Classifier: Programming Language :: Python :: 3
Classifier: Programming Language :: Python :: 3.7
Project-URL: Repository, https://github.com/olsonpm/case-conversion
